ejemplo.py
setup.py
Aplicacion_de_ejemplo.egg-info/PKG-INFO
Aplicacion_de_ejemplo.egg-info/SOURCES.txt
Aplicacion_de_ejemplo.egg-info/dependency_links.txt
Aplicacion_de_ejemplo.egg-info/top_level.txt