Metadata-Version: 1.0
Name: Aplicacion-de-ejemplo
Version: 0.1
Summary: Ejemplo del funcionamiento de distutils
Home-page: http://mundogeek.net/tutorial-python/
Author: Raul Gonzalez
Author-email: zootropo en gmail
License: GPL
Platform: UNKNOWN
